pyfds/__init__.py
pyfds/bst.py
pyfds/dlist.py
pyfds/list.py
pyfds/pqueue.py
pyfds/queue.py
pyfds/slist.py
pyfds/stack.py
pyfds/utils/__init__.py
pyfds/utils/dnode.py
pyfds/utils/node.py
pyfds/utils/pair.py
pyfds/utils/tnode.py
py_fds-3.5.3.dist-info/LICENSE
py_fds-3.5.3.dist-info/METADATA
py_fds-3.5.3.dist-info/WHEEL
py_fds-3.5.3.dist-info/top_level.txt
py_fds-3.5.3.dist-info/RECORD
