Metadata-Version: 2.1
Name: py-fds
Version: 3.5.3
Summary: Simple implementation of data structures for python
Home-page: https://github.com/FathiMalek/py-fds.git
Author: Abdelmalek Fathi
Author-email: abdelmalek.fathi.2001@gmail.com
Classifier: Development Status :: 7 - Inactive
Classifier: Programming Language :: Python :: 3
Classifier: License :: OSI Approved :: MIT License
Classifier: Operating System :: OS Independent
License-File: LICENSE
